[
  {
    "q": "(150 ÷ 5) × 3 - 20 = ?",
    "a": "70",
    "c": [
      "60",
      "70",
      "80"
    ],
    "img": ""
  },
  {
    "q": "ร้อยละ 20 ของ 200 คือเท่าไร?",
    "a": "40",
    "c": [
      "80",
      "40",
      "20"
    ],
    "img": ""
  },
  {
    "q": "1/2 + 1/4 = ?",
    "a": "3/4",
    "c": [
      "2/4",
      "1/8",
      "3/4"
    ],
    "img": ""
  },
  {
    "q": "0.25 ทำเป็นเศษส่วนได้อย่างไร?",
    "a": "1/4",
    "c": [
      "1/5",
      "1/4",
      "1/2"
    ],
    "img": ""
  },
  {
    "q": "มุมฉากมีขนาดกี่องศา?",
    "a": "90 องศา",
    "c": [
      "45 องศา",
      "90 องศา",
      "180 องศา"
    ],
    "img": ""
  },
  {
    "q": "พื้นที่สี่เหลี่ยมจัตุรัส ด้านละ 8 ซม. คือ?",
    "a": "64 ตร.ซม.",
    "c": [
      "16 ตร.ซม.",
      "32 ตร.ซม.",
      "64 ตร.ซม."
    ],
    "img": ""
  },
  {
    "q": "ปริมาตรทรงลูกบาศก์ กว้าง 3 ยาว 3 สูง 3 คือ?",
    "a": "27 ลบ.หน่วย",
    "c": [
      "27 ลบ.หน่วย",
      "18 ลบ.หน่วย",
      "9 ลบ.หน่วย"
    ],
    "img": ""
  },
  {
    "q": "ห.ร.ม. ของ 12 และ 18 คือ?",
    "a": "6",
    "c": [
      "6",
      "3",
      "2"
    ],
    "img": ""
  },
  {
    "q": "ค.ร.น. ของ 4 และ 6 คือ?",
    "a": "12",
    "c": [
      "10",
      "24",
      "12"
    ],
    "img": ""
  },
  {
    "q": "3² (3 ยกกำลัง 2) เท่ากับเท่าไร?",
    "a": "9",
    "c": [
      "9",
      "6",
      "27"
    ],
    "img": ""
  },
  {
    "q": "รถวิ่งความเร็ว 60 กม./ชม. ใน 2 ชม. ได้ระยะทาง?",
    "a": "120 กม.",
    "c": [
      "120 กม.",
      "180 กม.",
      "60 กม."
    ],
    "img": ""
  },
  {
    "q": "20% ของ 500 บาท คือ?",
    "a": "100 บาท",
    "c": [
      "100 บาท",
      "200 บาท",
      "50 บาท"
    ],
    "img": ""
  },
  {
    "q": "1/3 ของ 90 คือ?",
    "a": "30",
    "c": [
      "20",
      "60",
      "30"
    ],
    "img": ""
  },
  {
    "q": "เลขใดเป็นจำนวนเฉพาะ?",
    "a": "7",
    "c": [
      "7",
      "15",
      "9"
    ],
    "img": ""
  },
  {
    "q": "ผลบวกของมุมภายในรูปสี่เหลี่ยมคือ?",
    "a": "360 องศา",
    "c": [
      "180 องศา",
      "270 องศา",
      "360 องศา"
    ],
    "img": ""
  },
  {
    "q": "(8 + 4) × (10 - 5) = ?",
    "a": "60",
    "c": [
      "70",
      "50",
      "60"
    ],
    "img": ""
  },
  {
    "q": "0.1 × 100 = ?",
    "a": "10",
    "c": [
      "1",
      "100",
      "10"
    ],
    "img": ""
  },
  {
    "q": "น้ำหนัก 1.5 กิโลกรัม เท่ากับกี่กรัม?",
    "a": "1,500 กรัม",
    "c": [
      "1,500 กรัม",
      "15,000 กรัม",
      "150 กรัม"
    ],
    "img": ""
  },
  {
    "q": "ถ้าวันนี้วันจันทร์ อีก 10 วันคือวันอะไร?",
    "a": "วันพฤหัสบดี",
    "c": [
      "วันพุธ",
      "วันศุกร์",
      "วันพฤหัสบดี"
    ],
    "img": ""
  },
  {
    "q": "ซื้อของ 350 ลด 10% ต้องจ่ายเท่าไร?",
    "a": "315",
    "c": [
      "340",
      "315",
      "300"
    ],
    "img": ""
  }
]