[
  {
    "q": "สัตว์ตัวไหนร้อง เหมียวๆ?",
    "a": "แมว",
    "c": [
      "หมู",
      "แมว",
      "สุนัข"
    ],
    "img": "/images/science/cat.png"
  },
  {
    "q": "สัตว์ตัวไหนร้อง โฮ่งๆ?",
    "a": "สุนัข",
    "c": [
      "สุนัข",
      "ไก่",
      "แมว"
    ],
    "img": "/images/science/dog.png"
  },
  {
    "q": "สัตว์ตัวไหนร้อง ก๊าบๆ?",
    "a": "เป็ด",
    "c": [
      "นก",
      "เป็ด",
      "ไก่"
    ],
    "img": "/images/science/duck.png"
  },
  {
    "q": "สัตว์ตัวไหนร้อง อู๊ดๆ?",
    "a": "หมู",
    "c": [
      "หมู",
      "วัว",
      "ม้า"
    ],
    "img": "/images/science/pig.png"
  },
  {
    "q": "สัตว์ตัวไหนร้อง มอๆ?",
    "a": "วัว",
    "c": [
      "วัว",
      "แกะ",
      "แพะ"
    ],
    "img": "/images/science/cow.png"
  },
  {
    "q": "เราใช้อวัยวะใดในการมองดู?",
    "a": "ตา",
    "c": [
      "จมูก",
      "หู",
      "ตา"
    ],
    "img": "/images/science/eye.png"
  },
  {
    "q": "เราใช้อวัยวะใดในการฟังเสียง?",
    "a": "หู",
    "c": [
      "หู",
      "ตา",
      "ปาก"
    ],
    "img": "/images/science/ear.png"
  },
  {
    "q": "เราใช้อวัยวะใดในการดมกลิ่น?",
    "a": "จมูก",
    "c": [
      "จมูก",
      "มือ",
      "ปาก"
    ],
    "img": "/images/science/nose.png"
  },
  {
    "q": "เราใช้อวัยวะใดในการกินอาหาร?",
    "a": "ปาก",
    "c": [
      "หู",
      "จมูก",
      "ปาก"
    ],
    "img": "/images/science/mouth.png"
  },
  {
    "q": "เราใช้อวัยวะใดในการหยิบจับสิ่งของ?",
    "a": "มือ",
    "c": [
      "มือ",
      "หัว",
      "เท้า"
    ],
    "img": "/images/science/hand.png"
  },
  {
    "q": "สัตว์ใดมีงวงยาว?",
    "a": "ช้าง",
    "c": [
      "ม้า",
      "เสือ",
      "ช้าง"
    ],
    "img": "/images/science/elephant.png"
  },
  {
    "q": "สัตว์ใดมีคอยาว?",
    "a": "ยีราฟ",
    "c": [
      "ลิง",
      "ยีราฟ",
      "ม้าลาย"
    ],
    "img": "/images/science/giraffe.png"
  },
  {
    "q": "สัตว์ใดชอบกินกล้วย?",
    "a": "ลิง",
    "c": [
      "เสือ",
      "ปลา",
      "ลิง"
    ],
    "img": "/images/science/monkey.png"
  },
  {
    "q": "สัตว์ใดบินได้?",
    "a": "นก",
    "c": [
      "แมว",
      "นก",
      "สุนัข"
    ],
    "img": "/images/science/bird.png"
  },
  {
    "q": "สัตว์ใดว่ายน้ำ?",
    "a": "ปลา",
    "c": [
      "นก",
      "ปลา",
      "ไก่"
    ],
    "img": "/images/science/fish.png"
  },
  {
    "q": "อวัยวะใดใช้เดิน?",
    "a": "เท้า",
    "c": [
      "มือ",
      "ปาก",
      "เท้า"
    ],
    "img": "/images/science/foot.png"
  },
  {
    "q": "อวัยวะใดอยู่บนสุดของร่างกาย?",
    "a": "ศีรษะ (หัว)",
    "c": [
      "ศีรษะ (หัว)",
      "ท้อง",
      "เข่า"
    ],
    "img": "/images/science/head.png"
  },
  {
    "q": "ฟันมีสีอะไร?",
    "a": "สีขาว",
    "c": [
      "สีขาว",
      "สีดำ",
      "สีแดง"
    ],
    "img": "/images/science/teeth.png"
  },
  {
    "q": "สัตว์ใดมีกระดองแข็ง?",
    "a": "เต่า",
    "c": [
      "เต่า",
      "งู",
      "กบ"
    ],
    "img": "/images/science/turtle.png"
  },
  {
    "q": "สัตว์ใดกระโดดเก่งและมีกระเป๋าหน้าท้อง?",
    "a": "จิงโจ้",
    "c": [
      "กระต่าย",
      "จิงโจ้",
      "สิงโต"
    ],
    "img": "/images/science/kangaroo.png"
  }
]